LICENSE
LICENSE.txt
MANIFEST.in
README.md
requirements.txt
setup.py
DACOpt.egg-info/PKG-INFO
DACOpt.egg-info/SOURCES.txt
DACOpt.egg-info/dependency_links.txt
DACOpt.egg-info/requires.txt
DACOpt.egg-info/top_level.txt
dacopt/BO4AutoML.py
dacopt/DACOpt.py
dacopt/ObjectiveFunction.py
dacopt/ParamsExt.py
dacopt/SearchSpaceExt.py
dacopt/__init__.py
dacopt/stac/__init__.py
dacopt/stac/nonparametric_tests.py
dacopt/stac/parametric_tests.py
dacopt/stac/unit_tests.py