Metadata-Version: 2.1
Name: DACOpt
Version: 0.1.1
Summary: DACOpt: An Efficient Contesting Procedure for AutoML Optimization
Home-page: https://github.com/ECOLE-ITN/DACOpt
Author: Duc Anh Nguyen
Author-email: d.a.nguyen@liacs.leidenuniv.nl
License: GPL-3.0 License
Keywords: AutoML optimization Divide and conquer Bayesian Optimization
Platform: UNKNOWN
License-File: LICENSE
License-File: LICENSE.txt
